text2aks/__init__.py
text2aks/elements.py
text2aks/fonts/vazir/Vazirmatn-Black.ttf
text2aks/fonts/vazir/Vazirmatn-Bold.ttf
text2aks/fonts/vazir/Vazirmatn-ExtraBold.ttf
text2aks/fonts/vazir/Vazirmatn-ExtraLight.ttf
text2aks/fonts/vazir/Vazirmatn-Light.ttf
text2aks/fonts/vazir/Vazirmatn-Medium.ttf
text2aks/fonts/vazir/Vazirmatn-Regular.ttf
text2aks/fonts/vazir/Vazirmatn-SemiBold.ttf
text2aks/fonts/vazir/Vazirmatn-Thin.ttf
text2aks/fonts_data.py
text2aks/interfaces.py
text2aks/picture_maker.py
text2aks-0.1.1a1.dist-info/LICENSE
text2aks-0.1.1a1.dist-info/WHEEL
text2aks-0.1.1a1.dist-info/METADATA
text2aks-0.1.1a1.dist-info/RECORD
