Metadata-Version: 2.1
Name: text2aks
Version: 0.1.1a1
Summary: A simple python library to put text into an image.
Home-page: https://github.com/imanhpr/text2aks
License: MIT
Keywords: Pillow,Picture,Text
Author: ImanHpr
Author-email: imanhpr1999@gmail.com
Requires-Python: >=3.10,<4.0
Classifier: Development Status :: 2 - Pre-Alpha
Classifier: Intended Audience :: Developers
Classifier: Intended Audience :: Education
Classifier: Intended Audience :: Other Audience
Classifier: License :: OSI Approved :: MIT License
Classifier: Natural Language :: Arabic
Classifier: Natural Language :: Persian
Classifier: Operating System :: OS Independent
Classifier: Programming Language :: Python :: 3
Classifier: Programming Language :: Python :: 3.10
Classifier: Topic :: Software Development :: Libraries :: Python Modules
Requires-Dist: Pillow (>=9.1.0,<10.0.0)
Project-URL: Repository, https://github.com/imanhpr/text2aks
